Metadata-Version: 1.0
Name: FPyS
Version: 0.5
Summary: Amazon FPS Library
Home-page: http://fpys.achievewith.us
Author: Tim Freund
Author-email: tim@digital-achievement.com
License: MIT License
Platform: UNKNOWN
Classifier: Development Status :: 3 - Alpha
Classifier: Intended Audience :: Developers
Classifier: License :: OSI Approved :: MIT License
Classifier: Programming Language :: Python
Classifier: Topic :: Internet :: WWW/HTTP
Classifier: Topic :: Software Development :: Libraries :: Python Modules
